<?xml version="1.0"?>
<!DOCTYPE hibernate-mapping PUBLIC "-//Hibernate/Hibernate Mapping DTD 3.0//EN"
"http://hibernate.sourceforge.net/hibernate-mapping-3.0.dtd">
<!-- 
    Mapping file autogenerated by MyEclipse - Hibernate Tools
-->
<hibernate-mapping>
    <class name="org.chd.entity.Requirement" table="Requirement" schema="dbo" catalog="camis">
        <id name="subjectId" type="integer">
            <column name="SubjectId" />
            <generator class="assigned" />
        </id>
        <property name="content" type="java.lang.String">
            <column name="Content" />
        </property>
        <property name="information" type="java.lang.String">
            <column name="Information" />
        </property>
        <property name="specification" type="java.lang.String">
            <column name="Specification" />
        </property>
        <property name="charts" type="java.lang.String">
            <column name="Charts" />
        </property>
        <property name="schedule" type="java.lang.String">
            <column name="Schedule" />
        </property>
        <property name="reference" type="java.lang.String">
            <column name="Reference" />
        </property>
        <property name="addDate" type="date">
            <column name="AddDate" length="23" />
        </property>
    </class>
</hibernate-mapping>
